Metadata-Version: 1.1
Name: rosey-stats
Version: 1.2021.10.1.1336
Summary: Stats package for Python
Home-page: https://github.com/arose13/rosey-stats
Author: Stephen Rose
Author-email: me@stephenro.se
License: BSD
Platform: UNKNOWN
Classifier: Development Status :: 4 - Beta
Classifier: Intended Audience :: Developers
Classifier: Programming Language :: Python :: 3
Classifier: Topic :: Scientific/Engineering :: Artificial Intelligence
